setup.py
david_distributions.egg-info/PKG-INFO
david_distributions.egg-info/SOURCES.txt
david_distributions.egg-info/dependency_links.txt
david_distributions.egg-info/not-zip-safe
david_distributions.egg-info/top_level.txt
distributions/Binomialdistribution.py
distributions/Gaussiandistribution.py
distributions/Generaldistribution.py
distributions/__init__.py