Metadata-Version: 1.0
Name: david-distributions
Version: 0.1
Summary: Gaussian distributions
Home-page: UNKNOWN
Author: David Tan
Author-email: UNKNOWN
License: UNKNOWN
Platform: UNKNOWN
